install_preserve/__init__.py
install_preserve-0.1.0.dist-info/LICENSE
install_preserve-0.1.0.dist-info/METADATA
install_preserve-0.1.0.dist-info/WHEEL
install_preserve-0.1.0.dist-info/top_level.txt
install_preserve-0.1.0.dist-info/RECORD
