Metadata-Version: 2.1
Name: install-preserve
Version: 0.1.0
Summary: A Python library that helps prevent accidental overwrites of hand-compiled libraries
Home-page: https://github.com/manbehindthemadness/install-preserve
Author: Manbehindthemadness
Author-email: manbehindthemadness@gmail.com
Classifier: Programming Language :: Python :: 3
Classifier: License :: OSI Approved :: MIT License
Classifier: Operating System :: OS Independent
Requires-Python: >=3.0
License-File: LICENSE
